{
  "index_patterns": [
    "rc_insights"
  ],
  "template": {
    "settings": {
      "index": {
        "max_inner_result_window": 20000,
        "number_of_shards": 9,
        "mapping":{
            "total_fields": {
                "limit": "10000"
            }
        }
      }
    },
    "mappings": {
      "_source": {
        "enabled": true
      },
      "dynamic": false,
      "dynamic_templates": [
        {
          "strings_as_keyword": {
            "match_mapping_type": "string",
            "mapping": {
              "type": "keyword"
            }
          }
        },
        {
          "double": {
            "match_mapping_type": "double",
            "mapping": {
              "type": "double",
              "ignore_malformed": true
            }
          }
        },
        {
          "long": {
            "match_mapping_type": "long",
            "mapping": {
              "type": "long",
              "ignore_malformed": true
            }
          }
        }
      ],
      "properties": {
        "job_id": {
          "type": "long"
        },
        "insight_id": {
          "type": "long"
        },
        "integration_id": {
          "type": "keyword"
        },
        "integration_type": {
          "type": "keyword"
        },
        "provider_id": {
          "type": "keyword"
        },
        "query": {
          "type": "keyword"
        },
        "description": {
          "type": "keyword"
        },
        "schedule_uuid": {
          "type": "keyword"
        },
        "executed_at": {
          "type": "long"
        },
        "result": {
          "type": "long"
        },
        "resource_type": {
          "type": "keyword"
        },
        "resource_collection": {
          "type": "keyword"
        }
      }
    }
  },
  "_meta": {
    "description": "Insight index"
  }
}